<?xml version="1.0" encoding="UTF-8"?>
<addon id="repository.loiolog" name="loiolog Repository" version="1.0.0" provider-name="RubénSDFA1laberot">
    <extension point="xbmc.addon.repository" name="loiolog Repository">
        <dir>
            <info compressed="false">https://loioloio.github.io/loiolog/addons.xml</info>
            <checksum>https://loioloio.github.io/loiolog/addons.xml.md5</checksum>
            <datadir zip="true">https://loioloio.github.io/loiolog/</datadir>
        </dir>
    </extension>
    <extension point="xbmc.addon.metadata">
        <summary lang="es">Repositorio de loiolog</summary>
        <summary lang="en">loiolog Repository</summary>
        <description lang="es">Repositorio oficial para instalar y actualizar el addon loiolog.</description>
        <description lang="en">Official repository for installing and updating the loiolog addon.</description>
        <platform>all</platform>
        <assets>
            <icon>icon.png</icon>
        </assets>
    </extension>
</addon>
